mcplot/__init__.py
mcplot/_version.py
mcplot/argsort.py
mcplot/class_mcplot.py
mcplot/helper.py
mcplot/position.py
mcplot/romanliterals.py
mcplot/str2tex.py
mcplot/text2plot.py
mcplot/color/__init__.py
mcplot/color/brewer_palettes.py
mcplot/color/color.py
mcplot/color/freetone_palettes.py
mcplot/color/ipcc_palettes.py
mcplot/color/mathematica_palettes.py
mcplot/color/mcplot_palettes.py
mcplot/color/ncl_palettes.py
mcplot/color/oregon_palettes.py
mcplot/color/sron2012_palettes.py
mcplot/color/sron_palettes.py
mcplot/color/ufz_palettes.py
mcplot-2.2.dist-info/licenses/AUTHORS.rst
mcplot-2.2.dist-info/licenses/LICENSE
mcplot-2.2.dist-info/METADATA
mcplot-2.2.dist-info/WHEEL
mcplot-2.2.dist-info/top_level.txt
mcplot-2.2.dist-info/RECORD
